{
	"backtrace" : 0,
	"backtraceGraph" : 
	{
		"commands" : [],
		"files" : 
		[
			"extras/wrlview/CMakeLists.txt"
		],
		"nodes" : 
		[
			{
				"file" : 0
			}
		]
	},
	"id" : "wrlview_autogen::@e56124abfb0e470ca167",
	"isGeneratorProvided" : true,
	"name" : "wrlview_autogen",
	"paths" : 
	{
		"build" : "extras/wrlview",
		"source" : "extras/wrlview"
	},
	"sourceGroups" : 
	[
		{
			"name" : "",
			"sourceIndexes" : 
			[
				0
			]
		},
		{
			"name" : "CMake Rules",
			"sourceIndexes" : 
			[
				1
			]
		}
	],
	"sources" : 
	[
		{
			"backtrace" : 0,
			"isGenerated" : true,
			"path" : "build/extras/wrlview/CMakeFiles/wrlview_autogen",
			"sourceGroupIndex" : 0
		},
		{
			"backtrace" : 0,
			"isGenerated" : true,
			"path" : "build/extras/wrlview/CMakeFiles/wrlview_autogen.rule",
			"sourceGroupIndex" : 1
		}
	],
	"type" : "UTILITY"
}
